gwframe/__init__.py
gwframe/_core.cpp
gwframe/_core.cpython-313-x86_64-linux-gnu.so
gwframe/_version.py
gwframe/cli.py
gwframe/errors.py
gwframe/inspect.py
gwframe/operations.py
gwframe/read.py
gwframe/types.py
gwframe/write.py
gwframe/tests/__init__.py
gwframe/tests/conftest.py
gwframe/tests/test_basic.py
gwframe/tests/test_cli.py
gwframe/tests/test_complex_types.py
gwframe/tests/test_metadata.py
gwframe/tests/test_operations.py
gwframe/tests/test_read.py
gwframe/tests/test_roundtrip.py
gwframe/tests/test_time_slicing.py
gwframe/tests/test_write.py
gwframe.libs/libboost_atomic-3d2eb78f.so.1.75.0
gwframe.libs/libboost_chrono-29e9f5f7.so.1.75.0
gwframe.libs/libboost_date_time-76d26256.so.1.75.0
gwframe.libs/libboost_filesystem-0bf67256.so.1.75.0
gwframe.libs/libboost_log-eab1f83d.so.1.75.0
gwframe.libs/libboost_log_setup-97bbb1ff.so.1.75.0
gwframe.libs/libboost_program_options-df1494d5.so.1.75.0
gwframe.libs/libboost_regex-32b8141c.so.1.75.0
gwframe.libs/libboost_system-34bb126e.so.1.75.0
gwframe.libs/libboost_thread-5a8dcbc4.so.1.75.0
gwframe.libs/libcrypto-a07a2e9c.so.3.2.2
gwframe.libs/libframecpp-6d27d2ee.so.15.0.0
gwframe.libs/libframecpp3-99027d36.so.8.1.0
gwframe.libs/libframecpp4-513ec182.so.10.1.0
gwframe.libs/libframecpp6-919f6288.so.10.0.1
gwframe.libs/libframecpp7-d90f0217.so.6.0.0
gwframe.libs/libframecpp8-54e1f5e4.so.11.0.1
gwframe.libs/libframecppcmn-83ffaa31.so.12.1.0
gwframe.libs/libicudata-ffbbc3c9.so.67.1
gwframe.libs/libicui18n-089faaa2.so.67.1
gwframe.libs/libicuuc-7a7ee473.so.67.1
gwframe.libs/libldastoolsal-ab314135.so.7.1.0
gwframe-0.1.2.dist-info/METADATA
gwframe-0.1.2.dist-info/WHEEL
gwframe-0.1.2.dist-info/entry_points.txt
gwframe-0.1.2.dist-info/RECORD
gwframe-0.1.2.dist-info/licenses/LICENSE
