Metadata-Version: 2.2
Name: gwframe
Version: 0.1.2
Summary: High-level Python library to work with gravitational-wave frame (GWF) files, based on framecpp
Author-Email: Patrick Godwin <patrick.godwin@ligo.org>
Maintainer-Email: Patrick Godwin <patrick.godwin@ligo.org>
License: GPL-2.0-or-later
Classifier: Development Status :: 3 - Alpha
Classifier: Intended Audience :: Science/Research
Classifier: Intended Audience :: Developers
Classifier: License :: OSI Approved :: GNU General Public License v2 or later (GPLv2+)
Classifier: Natural Language :: English
Classifier: Operating System :: POSIX
Classifier: Operating System :: POSIX :: Linux
Classifier: Operating System :: MacOS
Classifier: Programming Language :: Python
Classifier: Programming Language :: Python :: 3
Classifier: Programming Language :: Python :: 3.10
Classifier: Programming Language :: Python :: 3.11
Classifier: Programming Language :: Python :: 3.12
Classifier: Programming Language :: Python :: 3.13
Classifier: Programming Language :: C++
Classifier: Topic :: Scientific/Engineering
Classifier: Topic :: Scientific/Engineering :: Astronomy
Classifier: Topic :: Scientific/Engineering :: Physics
Project-URL: Homepage, https://git.ligo.org/patrick.godwin/gwframe
Project-URL: Repository, https://git.ligo.org/patrick.godwin/gwframe
Project-URL: Documentation, https://git.ligo.org/patrick.godwin/gwframe
Project-URL: Issue Tracker, https://git.ligo.org/patrick.godwin/gwframe/issues
Requires-Python: >=3.10
Requires-Dist: numpy>=1.26
Provides-Extra: cli
Requires-Dist: typer>=0.10.0; extra == "cli"
Requires-Dist: rich>=13.0.0; extra == "cli"
Provides-Extra: test
Requires-Dist: gwframe[cli]; extra == "test"
Requires-Dist: pytest>=7.0; extra == "test"
Requires-Dist: pytest-cov>=4.0; extra == "test"
Provides-Extra: docs
Requires-Dist: mkdocs>=1.3; extra == "docs"
Requires-Dist: mkdocs-coverage>=0.2; extra == "docs"
Requires-Dist: mkdocs-gen-files>=0.3; extra == "docs"
Requires-Dist: mkdocs-literate-nav>=0.4; extra == "docs"
Requires-Dist: mkdocs-material-igwn; extra == "docs"
Requires-Dist: mkdocs-section-index>=0.3; extra == "docs"
Requires-Dist: mkdocstrings[python]; extra == "docs"
Requires-Dist: markdown-callouts>=0.2; extra == "docs"
Requires-Dist: markdown-exec>=0.5; extra == "docs"
Requires-Dist: toml>=0.10; extra == "docs"
Provides-Extra: lint
Requires-Dist: mypy>=1.0; extra == "lint"
Requires-Dist: mypy-extensions; extra == "lint"
Requires-Dist: pip; extra == "lint"
Requires-Dist: ruff>=0.1.0; extra == "lint"
Provides-Extra: dev
Requires-Dist: gwframe[test]; extra == "dev"
Requires-Dist: gwframe[lint]; extra == "dev"
Requires-Dist: gwframe[docs]; extra == "dev"
